kronicler-0.1.3.dist-info/METADATA
kronicler-0.1.3.dist-info/WHEEL
kronicler-0.1.3.dist-info/licenses/LICENSE
kronicler/__init__.py
kronicler/kronicler.cpython-311-aarch64-linux-gnu.so
kronicler-0.1.3.dist-info/RECORD
