Metadata-Version: 2.4
Name: kronicler
Version: 0.1.3
Classifier: Programming Language :: Rust
Classifier: Programming Language :: Python :: Implementation :: CPython
Classifier: Programming Language :: Python :: Implementation :: PyPy
Requires-Dist: starlette>=0.40.0,<0.48.0
License-File: LICENSE
Summary: Automatic performance capture and analysis for production applications in Python using a custom columnar database written in Rust.
Keywords: analytics,metrics,database,columnar
Home-Page: https://github.com/JakeRoggenbuck/kronicler
Author-email: Jake Roggenbuck <jakeroggenbuck2@gmail.com>
Maintainer-email: Jake Roggenbuck <jakeroggenbuck2@gmail.com>
License-Expression: MIT
Requires-Python: >=3.8
Project-URL: Repository, https://github.com/JakeRoggenbuck/kronicler
Project-URL: Homepage, https://github.com/JakeRoggenbuck/kronicler
